{
    "code": "65D01N01",
    "name": {
        "zh": "金融機構與市場",
        "en": "Financial Markets and Institutions"
    },
    "credit": "3",
    "type": "選修",
    "classes": [
        "四技國商三甲"
    ],
    "instructors": [
        "何啟銘"
    ],
    "schedule": [
        {
            "day": "週三",
            "period": "第1節",
            "location": "S415"
        },
        {
            "day": "週三",
            "period": "第2節",
            "location": "S415"
        },
        {
            "day": "週三",
            "period": "第3節",
            "location": "S415"
        }
    ],
    "hours": {
        "course": "3",
        "practice": "0"
    },
    "languages": [
        "1.英語",
        "◎全程外語教學"
    ],
    "certificationsSupport": [
        "無"
    ],
    "description": "By understanding the financial market system, combined with the events and information generated by the economic life environment, we can flexibly apply the theories to the real world and further reflect and transform them.",
    "prerequisites": "Economics",
    "syllabus": {
        "zh": "金融市場概論<br>金融市場的參與機構<br>金融制度<br>貨幣市場<br>股票市場<br>債劵市場<br>外匯市場<br>",
        "en": "Introduction of financial markets<br>Financial institutions<br>Financial system<br>Money market<br>Stock market<br>Bond market<br>Foreign market<br>"
    },
    "weeklySchedule": "",
    "exams": {
        "midterm": "",
        "final": "",
        "other": ""
    },
    "teachingAndAssessment": [
        {
            "objective": "能了解金融中介機構的種類、功能與風險",
            "teachingMethods": [
                "--"
            ],
            "assessmentMethods": [
                {
                    "method": "--",
                    "type": ""
                }
            ]
        },
        {
            "objective": "能了解金融工具的特性",
            "teachingMethods": [
                "--"
            ],
            "assessmentMethods": [
                {
                    "method": "--",
                    "type": ""
                }
            ]
        },
        {
            "objective": "能統整和應用相關財金知識來分析及解決財金實務與問題",
            "teachingMethods": [
                "--"
            ],
            "assessmentMethods": [
                {
                    "method": "--",
                    "type": ""
                }
            ]
        },
        {
            "objective": "能評析資料，有條理地表達和溝通，並建立正確的金融觀念與態度",
            "teachingMethods": [
                "--"
            ],
            "assessmentMethods": [
                {
                    "method": "--",
                    "type": ""
                }
            ]
        }
    ],
    "textbook": {
        "title": "",
        "author": "",
        "publisher": "",
        "year": "",
        "ISBN": "",
        "edition": ""
    },
    "referenceBooks": "",
    "teachingSoftware": "",
    "rules": ""
}